read_only_friday_checker/__init__.py
read_only_friday_checker/app.py
read_only_friday_checker/rof_api_checker.py
read_only_friday_checker/resources/PYPI_README.md
read_only_friday_checker/resources/images/read_only_friday_checker-128.png
read_only_friday_checker/resources/images/read_only_friday_checker-16.png
read_only_friday_checker/resources/images/read_only_friday_checker-256.png
read_only_friday_checker/resources/images/read_only_friday_checker-32.png
read_only_friday_checker/resources/images/read_only_friday_checker-512.png
read_only_friday_checker/resources/images/read_only_friday_checker-64.png
read_only_friday_checker-1.0.2.dist-info/METADATA
read_only_friday_checker-1.0.2.dist-info/WHEEL
read_only_friday_checker-1.0.2.dist-info/entry_points.txt
read_only_friday_checker-1.0.2.dist-info/licenses/LICENSE
read_only_friday_checker-1.0.2.dist-info/RECORD
