Metadata-Version: 2.4
Name: read_only_friday_checker
Version: 1.0.2
Summary: This checks to see if today is Read Only Friday.
Project-URL: repository, https://codeberg.org/melvinquick/read_only_friday_checker
Project-URL: issues, https://codeberg.org/melvinquick/read_only_friday_checker/issues
Author-email: Melvin Quick <melvinquick@proton.me>
License-Expression: MIT
License-File: LICENSE
Requires-Python: >=3.12
Requires-Dist: pyside6>=6.8.2.1
Requires-Dist: requests>=2.32.3
